kdelearn/__init__.py
kdelearn/kde.py
kdelearn/kernels.py
kdelearn-1.0.0.dist-info/LICENSE
kdelearn-1.0.0.dist-info/METADATA
kdelearn-1.0.0.dist-info/WHEEL
kdelearn-1.0.0.dist-info/top_level.txt
kdelearn-1.0.0.dist-info/RECORD
