Metadata-Version: 2.1
Name: kdelearn
Version: 1.0.0
Summary: Short description of ml methods based on kernel density estimation
Home-page: UNKNOWN
Author: Krystian Franus
Author-email: krystian.franus@gmail.com
License: MIT
Platform: UNKNOWN
Classifier: Intended Audience :: Science/Research
Classifier: Intended Audience :: Developers
Classifier: Programming Language :: Python :: 3
Classifier: Programming Language :: Python :: 3.6
Classifier: Programming Language :: Python :: 3.7
Classifier: Programming Language :: Python :: 3.8
Classifier: Programming Language :: Python :: 3.9
Classifier: License :: OSI Approved :: MIT License
Requires-Python: >=3.6
Requires-Dist: numpy (>=1.20.2)
Requires-Dist: notebook (>=6.3.0)
Requires-Dist: matplotlib (>=3.4.0)
Requires-Dist: jupyter-contrib-nbextensions (>=0.5.1)
Requires-Dist: scipy (>=1.6.2)
Requires-Dist: sphinx (>=3.5.4)
Requires-Dist: sphinx-rtd-theme (>=0.5.2)
Requires-Dist: flake8 (>=3.9.0)
